{"keys": ["", "34188", "173597", "211587", "130513", "162681", "9481", "209580", "40682", "99285", "104817", "82209", "39520", "100446", "104542", "199655", "26464", "7605", "156994", "9215", "132358", "157836", "130663", "15670", "95141", "52304", "130185", "29399", "215014", "38141", "151953", "59165", "183372", "119679", "153045", "203441", "44430", "86358", "50644", "188968", "109217", "56858", "20338", "194064", "115116", "856", "144776", "92653", "40126"], "data": {"156994": {"id": 156993}, "104542": {"id": 104541}, "59165": {"id": 59164}, "104817": {"id": 104816}, "194064": {"id": 194063}, "211587": {"id": 211586}, "56858": {"id": 56857}, "130185": {"id": 130184}, "20338": {"id": 20337}, "215014": {"id": 215013}, "39520": {"id": 39519}, "109217": {"id": 109216}, "203441": {"id": 203440}, "151953": {"id": 151952}, "44430": {"id": 44429}, "856": {"id": 855}, "199655": {"id": 199654}, "95141": {"id": 95140}, "38141": {"id": 38140}, "92653": {"id": 92652}, "173597": {"id": 173596}, "40126": {"id": 40125}, "52304": {"id": 52303}, "209580": {"id": 209579}, "40682": {"id": 40681}, "50644": {"id": 50643}, "29399": {"id": 29398}, "15670": {"id": 15669}, "115116": {"id": 115115}, "130513": {"id": 130512}, "132358": {"id": 132357}, "86358": {"id": 86357}, "130663": {"id": 130662}, "9481": {"id": 9480}, "119679": {"id": 119678}, "9215": {"id": 9214}, "162681": {"id": 162680}, "7605": {"id": 7604}, "100446": {"id": 100445}, "99285": {"id": 99284}, "26464": {"id": 26463}, "82209": {"id": 82208}, "144776": {"id": 144775}, "157836": {"id": 157835}, "34188": {"id": 34187}, "153045": {"id": 153044}, "183372": {"id": 183371}, "188968": {"id": 188967}}, "grid": ["                                                                ", "    !!!                                                  ##     ", "    !!!                               $$                 ##     ", "    !!     %%                        $$$        &&              ", "           %%                         $$        &&&             ", "     ''                                         &&              ", "     ''                              (((                        ", "     ''                              (((                     )) ", "      ***                             (                      )))", "      ***                                                    )) ", "       *                                       ++               ", "         ,,,                   --              +++              ", "         ,,,                  ---              ++               ", "          ,,      .            --                               ", "                 ...                                            ", "                 ...                    /                       ", "                                       ///                 000  ", "                        11             ///                 000  ", "                        111                                000  ", "                        11                                    22", "          3                                                   22", "         33    44                                             22", "         33   444      5    666                                 ", "               44     55    666                                 ", "                      55     6                                  ", "                                                                ", "                                                                ", "                                                                ", "                                  777                           ", "   88                             777                           ", "   88                                                           ", "                                              99                ", "                                :            999                ", "                               :::            99                ", "                               :::                              ", "                                                                ", "      ;;;                                <<<                    ", "      ;;;                                <<<  ==                ", "               >>                         <   ===               ", "               >>>            ??              ===               ", "               >>            ???                                ", "            @@                ??                                ", "  AA       @@@                                                  ", "  AA        @@                                              BB  ", "                                                       CC   BBB ", "                                                       CCC  BBB ", "       DD EE   FF                                      CC       ", "       DDDEEE  FFF                                              ", "       DDDEE   FF                                               ", "  GG                                                            ", "  GG                                                            ", "                                               HH               ", "          III                JJ               HHH               ", "          III       KKK     JJJ                HH               ", "                    KKK      JJ                                 ", "                     K                                          ", "                                                                ", "                                                                ", "                LL                         MM                   ", "                LL                         MMM   NN             ", "                LL         OOO             MMM   NN             ", "                           OOO                   NN             ", "          P                 O                                   ", "         PP     QQQ                                             "]}