{"keys": ["", "155938", "1850", "110810", "130656", "9767", "63616", "207980", "128677", "144593", "216579", "3510", "122888", "168818", "206445", "123569", "126765", "97935", "129230", "183997", "110519", "160689", "116116", "192603", "170394", "96371", "87427", "210236", "158523", "92710", "37233", "119899", "115048", "81848", "216863", "42608", "86558", "204799", "144160", "129355", "58308", "101469", "135130", "126493", "138334", "158107"], "data": {"110519": {"id": 110518}, "130656": {"id": 130655}, "158107": {"id": 158106}, "63616": {"id": 63615}, "158523": {"id": 158522}, "86558": {"id": 86557}, "216863": {"id": 216862}, "155938": {"id": 155937}, "58308": {"id": 58307}, "144593": {"id": 144592}, "96371": {"id": 96370}, "206445": {"id": 206444}, "1850": {"id": 1849}, "3510": {"id": 3509}, "168818": {"id": 168817}, "42608": {"id": 42607}, "138334": {"id": 138333}, "216579": {"id": 216578}, "126765": {"id": 126764}, "92710": {"id": 92709}, "210236": {"id": 210235}, "204799": {"id": 204798}, "129355": {"id": 129354}, "192603": {"id": 192602}, "144160": {"id": 144159}, "126493": {"id": 126492}, "160689": {"id": 160688}, "9767": {"id": 9766}, "170394": {"id": 170393}, "101469": {"id": 101468}, "81848": {"id": 81847}, "129230": {"id": 129229}, "116116": {"id": 116115}, "37233": {"id": 37232}, "87427": {"id": 87426}, "110810": {"id": 110809}, "97935": {"id": 97934}, "183997": {"id": 183996}, "135130": {"id": 135129}, "115048": {"id": 115047}, "122888": {"id": 122887}, "128677": {"id": 128676}, "207980": {"id": 207979}, "123569": {"id": 123568}, "119899": {"id": 119898}}, "grid": ["                                                                ", "                                                                ", "  !!!       ### $$                                              ", "  !!!   %%% ### $$                                         &&   ", "  !!    %%%  #                                             &&&  ", "                                                           &&   ", "           ''                                                   ", "           '''                                                  ", "           ''                                              ((   ", "                                                           ((   ", "                                 )))                       (    ", "                                 )))                            ", "                                  )                             ", "           **                        ++                         ", "           **                       +++     ,,                  ", "            *                        ++     ,,                  ", "                                            ,,                  ", "                                                                ", "                                                                ", "                                                                ", "                                                                ", "                                                                ", "                                                                ", "                                                                ", "                                                                ", "                                                                ", "            --                                                  ", "       ... ---                         //                       ", "       ...  --                         //                       ", "                                                                ", "                                                                ", "                                                0               ", "        11                            2        000              ", "        11   33                      222       000              ", "        11   333                     222                        ", "                                                                ", "                            444 55                              ", "           66               444 555                             ", "           666       777     4  55                              ", "           66        777                  88                    ", "                                   99    888                    ", "                       ::         999    888                    ", "                       ::  ;;;     99                           ", "                       ::  ;;;                                  ", "                            ;                                   ", "                                                                ", "  <<<        ==                                                 ", "  <<< >>     ===             ???                                ", "   < >>>     ===             ???                                ", "     >>>                  @@  ?                                 ", "                         @@@                                    ", "               AA         @@                                    ", "              AAA                                         BBB   ", "               AA                                         BBB   ", "CC                                     DD     EEE         BBB   ", "CC                                    DDD     EEE               ", "                      F   GGG          DD                H      ", "                     FFF  GGG          III              HHH     ", "              JJ     FFF               III      KKK     HHH     ", "              JJJ                       II      KKK             ", "              JJ                                                ", " L      M                                                       ", "LLL    MM                                       NN              ", "LLL    MM                                       NNN             "]}