{"keys": ["", "57117", "122323", "125723", "158416", "22168", "47533", "87144", "109695", "85450", "20726", "62798", "158905", "10523", "187158", "65728", "89068", "89096", "65369", "29071", "33221", "126260", "128722", "76559", "171048", "196177", "99070", "5039", "133613", "136130", "118968", "20939", "49850", "168107", "10790", "200894", "162016", "46760", "70486"], "data": {"65369": {"id": 65368}, "126260": {"id": 126259}, "5039": {"id": 5038}, "20939": {"id": 20938}, "57117": {"id": 57116}, "196177": {"id": 196176}, "10523": {"id": 10522}, "10790": {"id": 10789}, "158416": {"id": 158415}, "87144": {"id": 87143}, "122323": {"id": 122322}, "49850": {"id": 49849}, "125723": {"id": 125722}, "109695": {"id": 109694}, "128722": {"id": 128721}, "29071": {"id": 29070}, "47533": {"id": 47532}, "89068": {"id": 89067}, "20726": {"id": 20725}, "133613": {"id": 133612}, "136130": {"id": 136129}, "76559": {"id": 76558}, "65728": {"id": 65727}, "200894": {"id": 200893}, "89096": {"id": 89095}, "187158": {"id": 187157}, "22168": {"id": 22167}, "85450": {"id": 85449}, "118968": {"id": 118967}, "99070": {"id": 99069}, "162016": {"id": 162015}, "46760": {"id": 46759}, "168107": {"id": 168106}, "33221": {"id": 33220}, "70486": {"id": 70485}, "62798": {"id": 62797}, "158905": {"id": 158904}, "171048": {"id": 171047}}, "grid": ["                     !!                                         ", "                     !!!                                        ", "                                                                ", "                                                                ", "                      ##                  $$                    ", "                     ###                 $$$                    ", "                      ##                  $$                    ", "                                                                ", "                                                                ", "                                                                ", "                                     %%                         ", " &                     ''            %%                         ", "&&&           ((      '''            %%                         ", "&&&           (((      ''                                       ", "              ((                                                ", "                                                                ", "                                                          )))   ", "   **                         +++                         )))   ", "   **                         ++                                ", "   *          ,,                                            --  ", "             ,,,                     ..                     --  ", "              ,,                     ..                  /  --  ", "                                                         //     ", "                                                         //     ", "                                                                ", "                                                                ", "                                                                ", "                                                           00 11", "                                                           00 11", "                                                           00   ", "                                                                ", "                                                     222        ", "                       33                            222        ", "                 44   333          55                           ", "                 44   333          55                           ", "                                                   66           ", "                                                  666           ", "                                                   66           ", "                                                           777  ", "                                                           777  ", "                                                            7   ", "           888                                                  ", "           888                     99    ::                     ", "                                   99    ::                 ;;  ", "                                                            ;;  ", "                                                                ", "                                                           <<<  ", "                                                     ==    <<<  ", "                                                    ===         ", "                                                     ==         ", "                                                                ", "                                                                ", "                                                                ", "                     >>                                         ", "                    >>>   ??                      @             ", "                    >>>   ???                    @@@            ", "                          ??                     @@@            ", "                                                          AAA   ", "                            BBB           CC    DDD       AAA   ", "         E                  BBB           CC    DDD        A    ", "        EEE                               CC     D              ", "        EEE                                                     ", "                                                                ", "     FFF       GG                                               "]}