{"keys": ["108160", "", "26810", "74338", "207874", "179491", "41152", "147337", "162028", "89002", "97744", "113722", "119619", "84925", "177652", "64664", "35506", "160802", "124311", "130826", "27629", "141477", "150294", "111865", "166358", "152579", "207036", "9078", "21935", "87089", "150214", "27433", "111477", "143236", "21077", "17050", "74680", "44725", "69253", "39501", "123850", "182805", "27561", "76943", "115594", "189231"], "data": {"189231": {"id": 189230}, "87089": {"id": 87088}, "21077": {"id": 21076}, "152579": {"id": 152578}, "113722": {"id": 113721}, "124311": {"id": 124310}, "64664": {"id": 64663}, "74680": {"id": 74679}, "27433": {"id": 27432}, "39501": {"id": 39500}, "35506": {"id": 35505}, "27629": {"id": 27628}, "150294": {"id": 150293}, "166358": {"id": 166357}, "97744": {"id": 97743}, "76943": {"id": 76942}, "162028": {"id": 162027}, "44725": {"id": 44724}, "111477": {"id": 111476}, "111865": {"id": 111864}, "123850": {"id": 123849}, "177652": {"id": 177651}, "147337": {"id": 147336}, "182805": {"id": 182804}, "21935": {"id": 21934}, "207874": {"id": 207873}, "143236": {"id": 143235}, "130826": {"id": 130825}, "9078": {"id": 9077}, "17050": {"id": 17049}, "207036": {"id": 207035}, "89002": {"id": 89001}, "26810": {"id": 26809}, "115594": {"id": 115593}, "69253": {"id": 69252}, "74338": {"id": 74337}, "108160": {"id": 108159}, "27561": {"id": 27560}, "160802": {"id": 160801}, "141477": {"id": 141476}, "119619": {"id": 119618}, "41152": {"id": 41151}, "150214": {"id": 150213}, "84925": {"id": 84924}, "179491": {"id": 179490}}, "grid": ["   !!!!!!!!!!!!!!!!!!!!!!!##!!!!!!!!!!!!!!$$$!!!!!!!!!!!!!!!!!!!", "   !!!!!!!!!%%!!!!!!!!!!!###!!!!!!!!!!!!!!$$!!!!!!!!!!!!!!!!!!!!", "!!!!!!!!!!!!%%%!!!!!!!!!!!##!!!!!!!!!!!!!!!!!!!!!!!!!!!!!!!!!!!!", "!!!!!!!!!!!!%%!!!!!!!!!!!!!!!!!!!!!!!!!!!!!!!!!!!!!!!!!!!!!!!!!!", "!!!!!!!!!!!!!!!!!!!!!!!!!!!!!!!!!!!!!!!!!!!!!!!!!!!!!!!!!!!!!!!!", "!!!!!!!!!!!!!!!!!!!!!!!!!!!!!!!!!!!!!!!!!!!!!!!!!!!!!!!!!!!!!!!!", "!!!!!!!!!!!!!!!&&!!!!!!!!!!!!!!!!!!!!!!!!!!!''!!!!!!!!!!!!!!!!!!", "!!!!!!!!!!!!!!!&&&!!!!!!!!!!!!!!!!!!!!!!!!!'''!!!!!!!!!!!!!!!(((", "!!!!!!!!!!!!!!!&&&!!!!!!!!!!!!!!!!!!!!!!!!!!''!!!!!!!!!!!!!!!(((", "!!!!!!!!!!!!!!!!!!!!!!!!!!!!!!!!!!!!!!!!!!))!!!!!!!!!!!!!!!!!((!", "!!!!!!!!!!***!!!!!!!!!!!!!!!!!!!!!!!!!!!!!))!!!!!+!!!!!!!!!!!!!!", "!!!!!!!!!!***!!!!!!!!!!!!!!!!!!!!!!!!!!!!!))!!!!+++!!!!!!!!!!!!!", "!!!!!!!!!!!!!!!!!!!!!!!!!!!!!!!!!!!!!!!!!!!!!!!!+++!!!!!!!!!!!!!", "!!!!!!!!!!!!!!!!!!!!!!!!!!!!!!!!!!!!!!!!!!!!!!!!!!!!!!!!!!!!!,,!", "!!!!!!!!!!!!!!!!!!!!!!!!!!!!!!!!!!!!!!!!!!!!!!!!!!!---!!!!!!!,,,", "!!!!!!.!!!!!!!!!!!!!!!!!!!!!!!!!!!!!!!!!!!!!!!!!!!!---!!!!!!!,,!", "!!!!!...!!!!!!!!!!!!!!!!!!!!!!!!!!!!!!!!!!!!!!!!!!!!-!!!!!!!!!!!", "!!!!!...!!!!!!!!!!!!!!!!!!!!!!!!!!!!!!!!!!!!!!!!!!!!!!!!!!!!!!!!", "!!!!!!!!!!!!!!!!!!!!!!!!!!!!!!!!!!!!!!!!!!!!!!!!!!!!!!!!!!!!!!!!", "!!!!!!!!!!!!!!!!!!!!!!!!!!!!!!!!!!!!!!!!!!!!!!!!!!!!!!!!!!!!!!!!", "!!!!!!!!!!!!!!!!!!!!!!!!!!!!!!!!!!!!!!!!!!//!!!!!!!!!!!!!!!!!!!!", "!!!!!000!!!!!!!!!!!!!!!!!!!!!!!!!!!!!!!!!!//!!!!!!!!!!!!!!!!!!!!", "!!!!!000!!!!!!!!!!!!!!!!!!!!!!!!!!!!!!!!!!//!!!!!!!!!!!!!!!!!!!!", "!!!!!!!!!!!!!!!11!!!!!!!!!!!!!!!!!!!!!!!!!!!!!!!!!!!!!!!!!!!!!!!", "!!!!!!!!!!!!!!111!!!!!!!!!!!!!!!!!!!!!!!!!!!!!!!!!!!!!!!!!!!!!!!", "!!!!!!!!!!!!!!!!!!!!!!!!!!222!!!!!!!!!!!!!!!!!!!!!!!!!!!!!!!!!!!", "!!!!!!!!!!!!!!!!!!!!!!!!!!222!!!!!!!!!!!!!!!!!33!!!!!!!!!!!!!!!!", "!!!!!!!!!!!!!!!!!!!!!!!!!!!!!!!!!!!!444!!!!!!!33!!!!!!!!!!!!!!!!", "!!!!!!!!!!!!!!!!!!!!!!!!!!!!!!!!!!!!444!!!!!!!33!!!!!!!!!!!!!!!!", "!!!!!!55!!66!!!!!!!!!!!!777!!!!88!!!!!!!!!!!!!!!!!!!!!!!!!!!!!!!", "!!!!!!555!66!!!!!!!!!!!!777!!!888!!!!!!!!!!!!!!!!!!!!!!!!!!!!!!!", "!!!!!!55!!!!!!!!!!!!!!!!!!!!!!!88!!!!!!!!!!!!!!!!999!!!!!!!!!!!!", "!!!!!!!!!!!!:::!!!!!!!!!!!!!!!!!!!!!!!!!!!!!!!!!!999!!!!!!!!!!!!", "!!!!!!!!!!!!:::!!!!!!!!!!!!!!!!!!!!!!!!!;;!!!!!!!!!!!!!!!!!!!!!!", "!!!!!!!!!!!!:::!!!!!!!!!!!!!!!!!!!!!!!!!;;!!!!!!!!!!!!!!!!!!!!!!", "!!!!!!!!!!!!!!!!!!!!!!!!!!!!!!!!!!!!!!!!!!!!!!!!!!!!!!!!!!!!!!!!", "!!!!!!!!!!!!!!!!!!!!!!!!!!!<<<!!!!!!!!!!!!!!!!!!!!!!!!!!!!!!!!!!", "!!!!!!!!!!!!!!!!!!!!!!!!!!!<<<!!!!!!!!!!!!!!!!!!!!!!!!!!!!!!!!!!", "!!!==!!!!!!!!!!!!!!!!!!!!!!<<<!!!!!!!!!!!!!!>>!!!!!!!!!!!!!!!!!!", "!!!==!!!!!!!!!!!!!!!!!!!!!!!!!!!!!!!!!!!!!!!>>!!!!!!!!?!!!!!!!!!", "!!!==!!!!!!!!!!!!!!!!!!!!!!!!!!!!!!!@@!!!!!!>>!!!!!!!???!!!!!!!!", "!!!!!!!!!!!!!!!!!!!!!!!!!!!!!!!!!!!@@@!!!!!!!!!!!!!!!???!!!!!!!!", "!!!!!!!!!!!!!AAA!!!!!!!!!!!!!!!!!!!!@@!!!!!!!!!!!!!!!!!!!!!!!!!!", "!!!!!!!!!!!!!AAA!!!!!!!!!!!!!!!!!!!!!!!!!!!!!!!!!!!!!!!!!!!!!!!!", "!!!!!!!!!!!!!!!!!!!!!!!!!!!!!B!!!!!!!!!!!!!!!!!!!!!!!!!!!!!!!!!!", "!!!!!!!!!!!!!!!!!!!!!!!!!!!!BBB!!!!!!!!!!!!!!!!!!!!!!!!!!!!!!!!!", "!!!!!!!CC!!!!!!!!!!!!!!!!!!!BBB!!!!DD!!!!!!!!!!!!!!!!!!!!!!!!!!!", "!!!!!!!CCC!!!!!!!!!!!!!!!!!!!!!!!!!DD!!!!!!!!!!!!EE!!!!!!!!!!!!!", "!!!!!!!CC!!!!!!!!!!!!!!!!FF!!!!!!!!DD!!!!!!!!GGG!EEE!!!!!!!!!!!!", "!!!!!!!!!!!!HHH!!!!!!!!!FFF!!!!!!!!!!!!!!!!!!GGG!EE!!!!!!III!!!!", "!!!!!!!!!!!!HHH!!!!!!!!!FFF!!!!!!!!!!!!!!!!!!!!!!!!!!!!!!III!!!!", "!!!!!!!!!!!!!H!!!!!!!!!!!!!!!!!!!!!!!!!!!!!!!!!!!!!!!!!!!!II!!!!", "!!!!!!!!!!!!!!!!!!!!!!!!!!!!!!!!!!!!!!!!!!!!!!!!!!!!!!!!!!!!!!!!", "!!!!!!!!!!!!!!!!!!!!!!!!!!!!!!!!!!!!!!!!!!!!!!!!!!!!!!!!!!!!!!!!", "!!!!!!!JJ!!!!!!!!!!!!!!!!!!!!!!!!!!!!!!!!!!!!!!!!!!!!!!!!!!!!!!!", "!!!!!!!JJ!!!!!!!KKK!!!!!!!!!!!!!!!!!!!!!!!!!!!!!!!!!!!!!!!!!!!!!", "!!!!!!!JJ!!!!!!!KKK!!!!!!!!!!!!!!!!!!!!!!!!!!!!!!!!!!!!!!!!!!!!!", "!!!!!!!!!!!!!!!!!K!!!!!!!!!!!!!!!!!!!!!!!!!!!!!!!!!!!!!!!!L!!!!!", "!!!!!!!!!!!!!!!!!!!!!!!!!!!!!!!!M!!!!!!!!!!!!!!!!!!!!!!!!LLL!!!!", "!!!!!!!!!!!!!!!!!!!!!!!!!!!!!!!MMM!!!!!!!!!!!!!!!!!!!!!!!LLL!!!!", "!!!!!!!!!!!!!!!!!!!!!!!!!!!!!!!MMM!!!!!!!!!!!!!!!!!!!!!!!!!!!!!!", "!!!!!!!!!!!!!!!!!!!!!!!!!!!!!!!!!!!!!!!!!!!!!!!!!!!!!!!!!!!!!!!!", "!!!!!!!!!!!!!!!!N!!!!!!!!!!!!!!!!!!!!!!!!!!!!!!!!!!!!!!!!!!!!!!!", "!!!!!!!!!!!!!!!NNN!!!!!!!!!!!!!!!!!!!!!!!!!!!!!!!!!!!!!!!!!!!!!!"]}