{"keys": ["", "166965", "71923", "16116", "28567", "66955", "6685", "93534", "127820", "92956", "3719", "119942", "129074", "206961", "15952", "93261", "20373", "136935", "105992", "2550", "22156", "75827", "144068", "168929", "197788", "141936", "33391", "5733", "106963", "64147", "216581", "16352", "179824", "153273", "86454", "201633", "184842", "62452", "75095", "188026", "132469", "173752", "25829", "157265", "120326", "50967", "4783", "214252", "29921"], "data": {"179824": {"id": 179823}, "86454": {"id": 86453}, "75827": {"id": 75826}, "50967": {"id": 50966}, "28567": {"id": 28566}, "16352": {"id": 16351}, "22156": {"id": 22155}, "3719": {"id": 3718}, "188026": {"id": 188025}, "75095": {"id": 75094}, "4783": {"id": 4782}, "20373": {"id": 20372}, "33391": {"id": 33390}, "132469": {"id": 132468}, "144068": {"id": 144067}, "141936": {"id": 141935}, "136935": {"id": 136934}, "184842": {"id": 184841}, "120326": {"id": 120325}, "119942": {"id": 119941}, "6685": {"id": 6684}, "25829": {"id": 25828}, "71923": {"id": 71922}, "214252": {"id": 214251}, "206961": {"id": 206960}, "197788": {"id": 197787}, "15952": {"id": 15951}, "127820": {"id": 127819}, "105992": {"id": 105991}, "216581": {"id": 216580}, "129074": {"id": 129073}, "5733": {"id": 5732}, "153273": {"id": 153272}, "92956": {"id": 92955}, "62452": {"id": 62451}, "66955": {"id": 66954}, "201633": {"id": 201632}, "2550": {"id": 2549}, "168929": {"id": 168928}, "157265": {"id": 157264}, "16116": {"id": 16115}, "166965": {"id": 166964}, "64147": {"id": 64146}, "106963": {"id": 106962}, "93261": {"id": 93260}, "93534": {"id": 93533}, "29921": {"id": 29920}, "173752": {"id": 173751}}, "grid": ["          !!!                                                   ", "          !!            ##                                      ", "                        ###                                     ", "                        ##                                      ", "                                                                ", "                                 $                              ", "                                $$$                             ", "   %%%                          $$$                             ", "   %%%                                                 &&&      ", "    %                                                  &&&      ", "                    ''            ((            ))              ", "                    ''            ((            )))             ", "                    ''            ((            ))              ", "                                                                ", "                                 ***        ++   ,,             ", "                                 ***        ++  ,,,       --    ", "                                            ++   ,,       --    ", "                                                          --    ", "                                ...                             ", "                           ///  ...                             ", "                           ///   .                              ", "                            /                                   ", "                                                                ", "                        00                                     1", "                        000                                   11", "               222      00                                     1", "               222                                              ", "                2                  33    44                     ", "                   5               33    444                    ", "                  555              33    44                     ", "                  555         66                                ", "           777            888 666           9                   ", "           777            888 666 :        999                  ", "            7   ;;         8     :::       999                  ", "      <<<       ;;;       ==     :::                            ", "      <<<       ;;        ===                                   ", "                          ==                                    ", "                                             >>>    ???       @@", "  AA                         BB              >>>    ???       @@", "  AA                         BB                      ?         @", "                                                                ", "                                                                ", "                                                               C", "                                                               C", "                                                               C", "                        DD                                      ", "       EE        FFF    DDD                                     ", "       EE        FFF    DD                                      ", "       EE                                                       ", "                                             GG                 ", "       HH                                    GG                 ", "       HHH                             II                       ", "       HHH                    JJ       III              KK      ", "                              JJ       II              KKK      ", "                                                        KK      ", "                                               L                ", "                                              LLL          MMM  ", "                           NNN                LLL          MMM  ", "                           NNN                              M   ", "                            NN                                  ", "                   OO                       PPP                 ", "                  OOO             QQ        PPP                 ", "                  OOO             QQQ       PP                  ", "                                  QQ                            "]}