{"keys": ["", "43141", "32304", "92565", "193342", "31775", "85160", "145070", "164570", "153797", "38982", "26521", "116580", "174447", "182657", "33483", "53310", "31834", "213312", "140322", "79170", "67607", "154703", "104965", "86", "75845", "12282", "114642", "33988", "20542", "155703", "36758", "20491", "91434", "209499", "68509", "201812", "13246", "196941", "56584", "20369", "187074", "174475", "216366", "114532", "76525", "93926", "162248", "91507", "105462", "169560", "187667", "183585", "16046", "68716", "100598", "64504", "497", "12276", "97697", "154572", "42974", "127262", "68935", "114364", "32444", "116873", "16030", "172620", "36413", "60649", "58004", "21507", "48731", "26072", "150843", "77611", "67187", "18805", "197436", "72622", "216851", "108109", "75780", "74104", "178348", "23471", "175516", "72888", "112184", "51576", "133878", "29491", "8627", "26182", "157601", "53422"], "data": {"53310": {"id": 53309}, "8627": {"id": 8626}, "497": {"id": 496}, "108109": {"id": 108108}, "26072": {"id": 26071}, "51576": {"id": 51575}, "32444": {"id": 32443}, "13246": {"id": 13245}, "105462": {"id": 105461}, "216366": {"id": 216365}, "33988": {"id": 33987}, "12276": {"id": 12275}, "32304": {"id": 32303}, "33483": {"id": 33482}, "23471": {"id": 23470}, "56584": {"id": 56583}, "72888": {"id": 72887}, "175516": {"id": 175515}, "18805": {"id": 18804}, "20369": {"id": 20368}, "112184": {"id": 112183}, "68935": {"id": 68934}, "67607": {"id": 67606}, "72622": {"id": 72621}, "155703": {"id": 155702}, "42974": {"id": 42973}, "197436": {"id": 197435}, "53422": {"id": 53421}, "114364": {"id": 114363}, "86": {"id": 85}, "150843": {"id": 150842}, "21507": {"id": 21506}, "140322": {"id": 140321}, "77611": {"id": 77610}, "154703": {"id": 154702}, "36758": {"id": 36757}, "75780": {"id": 75779}, "187667": {"id": 187666}, "91507": {"id": 91506}, "154572": {"id": 154571}, "174475": {"id": 174474}, "31775": {"id": 31774}, "145070": {"id": 145069}, "216851": {"id": 216850}, "58004": {"id": 58003}, "64504": {"id": 64503}, "93926": {"id": 93925}, "153797": {"id": 153796}, "157601": {"id": 157600}, "162248": {"id": 162247}, "187074": {"id": 187073}, "76525": {"id": 76524}, "75845": {"id": 75844}, "68716": {"id": 68715}, "29491": {"id": 29490}, "26182": {"id": 26181}, "169560": {"id": 169559}, "201812": {"id": 201811}, "74104": {"id": 74103}, "38982": {"id": 38981}, "60649": {"id": 60648}, "133878": {"id": 133877}, "91434": {"id": 91433}, "196941": {"id": 196940}, "183585": {"id": 183584}, "67187": {"id": 67186}, "104965": {"id": 104964}, "26521": {"id": 26520}, "172620": {"id": 172619}, "114532": {"id": 114531}, "209499": {"id": 209498}, "97697": {"id": 97696}, "43141": {"id": 43140}, "85160": {"id": 85159}, "79170": {"id": 79169}, "16030": {"id": 16029}, "213312": {"id": 213311}, "48731": {"id": 48730}, "116580": {"id": 116579}, "20542": {"id": 20541}, "182657": {"id": 182656}, "127262": {"id": 127261}, "164570": {"id": 164569}, "114642": {"id": 114641}, "20491": {"id": 20490}, "100598": {"id": 100597}, "36413": {"id": 36412}, "16046": {"id": 16045}, "12282": {"id": 12281}, "31834": {"id": 31833}, "193342": {"id": 193341}, "174447": {"id": 174446}, "178348": {"id": 178347}, "116873": {"id": 116872}, "92565": {"id": 92564}, "68509": {"id": 68508}}, "grid": ["           !            ###$$$        %%&&&                     ", "          !!!           ### $$        %%&&&                     ", "          !!!                                                   ", "         ''   (((       ))        **                            ", "         '''  (((   +   )))       ***  ,,                       ", "         '' -- (   +++  )))       **  ,,,                       ", "     ...   ---     +++     /           ,,                       ", "     ...    --            ///    00  11                         ", "      .               22  ///    00 111                         ", "      333            222             11                         ", "   44 333            222 55                                     ", "   444 3                 55 66                                  ", "   44                    55666                                  ", "            77              66  888      9                      ", "  ::        777                 888     999                     ", " :::    ;;  77           <<<            999                     ", "  ::    ;;; ==           <<<                                    ", "        ;;  ===                          >>                     ", "??          ==                        @@ >>>                    ", "??                  AAA              @@@ >>                     ", "?                   AAA   BB          @@                        ", "   C DDD             A    BB   EEE FFF                          ", "GGCCCDDD                  BB   EEE FFF                          ", "GGCCC            HH    III          F                           ", "G                HH    III     JJ       KK                      ", "                       II      JJJ      KKK                     ", "                               JJ   LLL KK                      ", "                             MMM    LLL NN                      ", "            OO   PP          MMM        NN                      ", "           OOO   PP           M         NN                      ", " QQQ       OOO RR   SSS  TT                                     ", " QQQ           RR   SSS  TTT                                    ", "  Q UU         RR        TT                                     ", "    UU                              V                           ", "    UU WW                       XX VVV                          ", "      WWW  YYY                  XX VVV                          ", "       WW  YYY                  XX                              ", "     ZZ           [[[  ]]      ^   __                           ", "    ZZZ           [[[  ]]     ^^^  ___                          ", "     ZZ      ``        ]]     ^^^  __     aaa                   ", "            ```                           aaa                   ", "             ``                       b                         ", "                    cc    dd         bbb                        ", "                   ccc   ddd      eeebbb                        ", "                    cc    dd   ff eee                           ", "   gg     hhh                  ff                               ", "   gg     hhh          i       ff                               ", "           h          iii       jjj                             ", "             kk    llliii       jjj      mm                     ", "   nn        kkk o  ll                   mmm                    ", "  nnn        kk ooopp                    mmm                    ", "   n            ooopp qqq          rr                           ", "sss       ttt      pp qqq          rr                           ", "sss       ttt          qq                                       ", "           t                                                    ", "  uu    vv           www           xx                           ", "  uuu   vv           www           xx   yy                      ", "  uu    vv            w            xx  yyy z                    ", "  {                                     yyzzz                   ", " {{{                                      zzz                   ", " {{                |||               }}                         ", "                   |||    ~~     \u007f\u007f  }}}                        ", "   \u0080\u0080  \u0081\u0081           ||    ~~~    \u007f\u007f\u007f }} \u0082\u0082\u0082                     ", "  \u0080\u0080\u0080 \u0081\u0081\u0081                 ~~      \u007f     \u0082\u0082\u0082                     "]}