{"keys": ["", "79794", "216702", "47249", "72609", "45165", "208265", "181113", "13868", "54182", "56365", "47206", "88616", "204226", "59986", "33631", "50599", "135740", "168542", "165235", "75954", "14516", "134506", "192840", "37624", "23476", "125770", "133137", "176186", "31336", "71623", "13848", "53359", "175736"], "data": {"79794": {"id": 79793}, "181113": {"id": 181112}, "204226": {"id": 204225}, "72609": {"id": 72608}, "47206": {"id": 47205}, "53359": {"id": 53358}, "125770": {"id": 125769}, "192840": {"id": 192839}, "168542": {"id": 168541}, "88616": {"id": 88615}, "14516": {"id": 14515}, "71623": {"id": 71622}, "133137": {"id": 133136}, "134506": {"id": 134505}, "75954": {"id": 75953}, "23476": {"id": 23475}, "31336": {"id": 31335}, "13868": {"id": 13867}, "45165": {"id": 45164}, "13848": {"id": 13847}, "54182": {"id": 54181}, "50599": {"id": 50598}, "175736": {"id": 175735}, "37624": {"id": 37623}, "208265": {"id": 208264}, "165235": {"id": 165234}, "216702": {"id": 216701}, "135740": {"id": 135739}, "33631": {"id": 33630}, "59986": {"id": 59985}, "56365": {"id": 56364}, "47249": {"id": 47248}, "176186": {"id": 176185}}, "grid": ["                                                                ", "                                                                ", "                                                                ", "                           !!!                                  ", "                           !!!                                  ", "                            !                                   ", "                                                   ##           ", "                                                   ##           ", "                                                   ##           ", "                                                                ", "                         $$                                     ", "                    %%% $$$                                     ", " &&&                %%%  $$                     ''              ", " &&&                                            '''             ", "  &                             ((              ''              ", "                                ((                              ", "                                          )  *                  ", "                                         )))***                 ", "                      +++                )) ***                 ", "                      +++                                       ", "                                           ,,                   ", "                                           ,,                   ", "      ---                               .. ,,                   ", "      ---                              ...                      ", "       -  //                            .                       ", "          //                                00                  ", "          //                                00     1            ", "                                            00    111           ", "                                                  111        222", "                                                             222", "             333                                                ", "             333                                        44      ", "                                      5 666            444      ", "                                     555666             44      ", "                                     55566           777        ", "                                                     777        ", "                              88                                ", "99                            88                                ", "999                           88                                ", "99                                                              ", "                                                                ", "                         ::                                     ", "                         :::                                    ", "                         ::                                     ", "                                                                ", "                                                                ", "                                                                ", "             ;;;                                                ", "             ;;;  <<<   ==                                      ", " >>           ;   <<<  ===                              ??      ", " >>                     ==                              ??      ", " >>                                                     ??      ", "                                                                ", "                                                                ", "                                                                ", "                                                                ", "                                                                ", "                                                                ", "                                                                ", "                     @@                                         ", "                    @@@                                         ", "                    @@@                          AAA            ", "        BBB                                      AAA            ", "        BBB                                       AA            "]}