{"keys": ["", "141837", "46892", "41294"], "data": {"41294": {"id": 41293}, "141837": {"id": 141836}, "46892": {"id": 46891}}, "grid": ["                                                                ", "                                                                ", "                                                                ", "                                                                ", "                                                                ", "                                                                ", "                                                                ", "        !!!                                                     ", "      ##!!!                                                     ", "      ## !                                                      ", "      ##                                                        ", "      $$                                                        ", "     $$$                                                        ", "      $$                                                        ", "                                                                ", "                                                                ", "                                                                ", "                                                                ", "                                                                ", "                                                                ", "                                                                ", "                                                                ", "                                                                ", "                                                                ", "                                                                ", "                                                                ", "                                                                ", "                                                                ", "                                                                ", "                                                                ", "                                                                ", "                                                                ", "                                                                ", "                                                                ", "                                                                ", "                                                                ", "                                                                ", "                                                                ", "                                                                ", "                                                                ", "                                                                ", "                                                                ", "                                                                ", "                                                                ", "                                                                ", "                                                                ", "                                                                ", "                                                                ", "                                                                ", "                                                                ", "                                                                ", "                                                                ", "                                                                ", "                                                                ", "                                                                ", "                                                                ", "                                                                ", "                                                                ", "                                                                ", "                                                                ", "                                                                ", "                                                                ", "                                                                ", "                                                                "]}