{"keys": ["", "180150", "142894", "173495", "205653", "210328", "11204", "132659", "69718", "24682", "166952", "73080", "14011", "63843", "122607", "33991", "156177", "39628", "111617", "60490", "138136", "139332", "203114", "48067", "55703", "59702", "94957", "5000", "149564", "143583", "142598", "48288", "64971", "171949", "16939", "27016", "32050", "3018", "78588", "152768", "201772", "54495", "165625", "19202", "80679", "216338", "174423", "109143", "55975", "50979", "145334", "29429", "33772", "21248", "175037", "16300", "3982", "89012"], "data": {"54495": {"id": 54494}, "174423": {"id": 174422}, "171949": {"id": 171948}, "203114": {"id": 203113}, "111617": {"id": 111616}, "59702": {"id": 59701}, "19202": {"id": 19201}, "122607": {"id": 122606}, "14011": {"id": 14010}, "143583": {"id": 143582}, "11204": {"id": 11203}, "55975": {"id": 55974}, "16939": {"id": 16938}, "89012": {"id": 89011}, "165625": {"id": 165624}, "80679": {"id": 80678}, "139332": {"id": 139331}, "64971": {"id": 64970}, "152768": {"id": 152767}, "32050": {"id": 32049}, "60490": {"id": 60489}, "69718": {"id": 69717}, "173495": {"id": 173494}, "55703": {"id": 55702}, "94957": {"id": 94956}, "73080": {"id": 73079}, "5000": {"id": 4999}, "142894": {"id": 142893}, "63843": {"id": 63842}, "29429": {"id": 29428}, "145334": {"id": 145333}, "180150": {"id": 180149}, "109143": {"id": 109142}, "201772": {"id": 201771}, "48067": {"id": 48066}, "16300": {"id": 16299}, "48288": {"id": 48287}, "166952": {"id": 166951}, "21248": {"id": 21247}, "132659": {"id": 132658}, "205653": {"id": 205652}, "3018": {"id": 3017}, "50979": {"id": 50978}, "78588": {"id": 78587}, "216338": {"id": 216337}, "27016": {"id": 27015}, "210328": {"id": 210327}, "39628": {"id": 39627}, "24682": {"id": 24681}, "33991": {"id": 33990}, "156177": {"id": 156176}, "33772": {"id": 33771}, "142598": {"id": 142597}, "175037": {"id": 175036}, "138136": {"id": 138135}, "149564": {"id": 149563}, "3982": {"id": 3981}}, "grid": [" !!                             ###                             ", " !!                   $$        ##                              ", "                     $$$              %                       &&", "        '             $$   ((())     %%%                      &&", "       '''                 ((())     %%%                      &&", "       '''              **    ))                                ", "                        ***                                     ", "+++                     **                                      ", "+++                                           ,, ---            ", " +                                           ,,, ---            ", "                              ...             ,, --             ", "                ///           ...                         00    ", "                ///            .                         000    ", "                 /          11                            00    ", "                            111                                 ", "                            11                      22        33", "                                                   222       333", "                     44                             22        3 ", "                    444      555                                ", "                   6 44      555                        77 888  ", "                  66                                    777888  ", "                  66                                999 77  8   ", "                                                    999         ", "                                                                ", "                                                              ::", "   ;;                                                 <<<     ::", "   ;;  ==                                >>           <<<       ", "   ;  ===                               >>>              ?      ", "       ==                                >>             ???     ", "                                               @@@      ???     ", "  AAA                                          @@@              ", "  AAA                                                  BB       ", "   A                                                   BBB      ", "                                                       BB       ", "                                                                ", "                                                                ", "                                                                ", "                             CCC                                ", "                             CCC         DDD                    ", "                              C          DDD                    ", "                     EE                   D               FF    ", "                GG  EEE                               H   FF    ", "               GGG   EE                              HH         ", "                GG                                   HH         ", "                       I                                        ", "                      III                                       ", "                      III                                       ", "                                              JJJ               ", "                                      KK      JJJ     L         ", "                                      KKK      J     LLL        ", "  MMM   NNN                         OOKKK   PP       LLL        ", "  MMM   NNN                        OOO      PP             QQ   ", "                                    OO      PP            QQQ   ", "                            RRR                            QQ   ", "                            RRR                     S           ", "                                                   SSS          ", "                              TTT                  SSS          ", "        UUU                   TTT                               ", "        UUU                   TT         VV          WW         ", " XXX     U                               VV         WWW         ", " XXX                                     VV  YYY    WWW         ", "  X                          ZZ              YYY                ", "                            ZZZ                                 ", "                             ZZ                                 "]}