{"keys": ["", "100654", "201543", "203918", "77054", "11624", "191959", "95190", "195607", "158360", "101015", "125647", "212814", "72661", "156704", "198754", "11761", "135915", "163148", "179709", "51613", "180851", "123676", "161186", "17930", "91159", "150320", "16174", "170446", "20843", "59701", "144125", "93938", "179448", "36948", "124081", "6082", "214425", "156484", "101352", "115159", "21880", "82747", "123282", "113657", "61509", "212512", "213907"], "data": {"124081": {"id": 124080}, "179709": {"id": 179708}, "20843": {"id": 20842}, "59701": {"id": 59700}, "170446": {"id": 170445}, "156484": {"id": 156483}, "212814": {"id": 212813}, "161186": {"id": 161185}, "6082": {"id": 6081}, "93938": {"id": 93937}, "213907": {"id": 213906}, "203918": {"id": 203917}, "191959": {"id": 191958}, "158360": {"id": 158359}, "144125": {"id": 144124}, "150320": {"id": 150319}, "115159": {"id": 115158}, "180851": {"id": 180850}, "82747": {"id": 82746}, "195607": {"id": 195606}, "163148": {"id": 163147}, "156704": {"id": 156703}, "100654": {"id": 100653}, "201543": {"id": 201542}, "214425": {"id": 214424}, "11624": {"id": 11623}, "101015": {"id": 101014}, "51613": {"id": 51612}, "11761": {"id": 11760}, "61509": {"id": 61508}, "179448": {"id": 179447}, "77054": {"id": 77053}, "36948": {"id": 36947}, "212512": {"id": 212511}, "125647": {"id": 125646}, "123282": {"id": 123281}, "17930": {"id": 17929}, "135915": {"id": 135914}, "95190": {"id": 95189}, "123676": {"id": 123675}, "113657": {"id": 113656}, "91159": {"id": 91158}, "21880": {"id": 21879}, "16174": {"id": 16173}, "101352": {"id": 101351}, "72661": {"id": 72660}, "198754": {"id": 198753}}, "grid": ["                           !!!                                  ", "                           !!!                                  ", "                                                       ##       ", "                                                 $     ###      ", "                                                $$$    ###      ", "                                                $$$             ", "                                                     %%%        ", "                                             &       %%%        ", "                                            &&&                 ", "                                            &&&               ''", "                                                              ''", "                                                              ''", "                                                                ", "                          (                                     ", "                         (((                                    ", ")))    ***               (((                +++                 ", ")))    ***                                  +++         ,,      ", " )                 -                    ...     ///     ,,,     ", "                  ---                   ...     ///     ,,      ", "                  ---                    .       /              ", "                                                                ", "               00                                1              ", "               00                               111             ", "               2                                 11             ", "              222                                               ", "              222                                               ", "33       44                               555                   ", "33       444    66          7             555                  8", "33       44    666         777             5             999   8", "                66         777                           999   8", "                                                                ", "                         :                                      ", "                        :::      ;;   <<<                       ", "                         ::      ;;;  <<<           =           ", "                                 ;;   <<           ===          ", "                                                   ===        >>", "                         ??             @@                    >>", "                         ??             @@@                   >>", "                         ??             @@                      ", "A                       B                                       ", "AA          CC         BBB                                      ", "AA         CCC         BBB                                      ", "            CC                                                  ", "                    DD                                          ", "                    DDDEEE                                      ", "                    DD EEE                                      ", "                                                                ", "                                              FF                ", "                 GG                          FFF                ", "                 GG   HH                      FF                ", "                 GG  HHH                                        ", "                      HH                                 III    ", "                                                         III    ", "                             J                            I     ", "                            JJJ                          KKK    ", "                            JJJ                          KKK    ", "                                                          KK    ", "                                                                ", "                   LL                              MMM          ", "                  LLL                              MMM          ", "                  LLL           N                   MM       OO ", "                               NNN                          OOO ", "                               NNN                   PPP     OO ", "                                                     PPP        "]}